{
  "data": [
    {
      "title": "Python for Financial Analysis Next and Algorithmic Trading",
      "category": "Python",
      "Author": {
        "name": "Adam Smith",
        "post": "Python Developer"
      },
      "stars": 4.5,
      "youtubeVideoId": "abcdef12345"
    },
    {
      "title": "Machine Learning with Scikit-Learn",
      "category": "Machine Learning",
      "Author": {
        "name": "Emily Johnson",
        "post": "Data Scientist"
      },
      "stars": 4.2,
      "youtubeVideoId": "ghijkl67890"
    },
    {
      "title": "JavaScript for Web Development",
      "category": "JavaScript",
      "Author": {
        "name": "David Brown",
        "post": "Web Developer"
      },
      "stars": 4.0,
      "youtubeVideoId": "mnopqr12345"
    },
    {
      "title": "Introduction to Data Science",
      "category": "Data Science",
      "Author": {
        "name": "Jennifer Lee",
        "post": "Data Scientist"
      },
      "stars": 4.8,
      "youtubeVideoId": "stuvwx67890"
    },
    {
      "title": "C++ Programming Essentials",
      "category": "C++",
      "Author": {
        "name": "Michael Johnson",
        "post": "Software Engineer"
      },
      "stars": 4.3,
      "youtubeVideoId": "yzabcd12345"
    },
    {
      "title": "Artificial Intelligence and Machine Learning Basics",
      "category": "Machine Learning",
      "Author": {
        "name": "Sophia White",
        "post": "AI Researcher"
      },
      "stars": 4.6,
      "youtubeVideoId": "efghij67890"
    },
    {
      "title": "Front-End Web Development with React",
      "category": "JavaScript",
      "Author": {
        "name": "Daniel Smith",
        "post": "Front-End Developer"
      },
      "stars": 4.7,
      "youtubeVideoId": "klmnop12345"
    },
    {
      "title": "Data Analysis with Pandas",
      "category": "Data Science",
      "Author": {
        "name": "Emma Davis",
        "post": "Data Analyst"
      },
      "stars": 4.4,
      "youtubeVideoId": "qrstuv67890"
    },
    {
      "title": "Java Programming for Beginners",
      "category": "Java",
      "Author": {
        "name": "John Brown",
        "post": "Software Engineer"
      },
      "stars": 4.1,
      "youtubeVideoId": "wxyzab12345"
    },
    {
      "title": "Deep Learning Fundamentals",
      "category": "Machine Learning",
      "Author": {
        "name": "Alex Smith",
        "post": "AI Researcher"
      },
      "stars": 4.9,
      "youtubeVideoId": "1234567890"
    }
  ]
}
